pg_data_etl/__init__.py
pg_data_etl/cli.py
pg_data_etl/database/__init__.py
pg_data_etl/database/actions/__init__.py
pg_data_etl/database/actions/admin.py
pg_data_etl/database/actions/backup.py
pg_data_etl/database/actions/copy.py
pg_data_etl/database/actions/data_export.py
pg_data_etl/database/actions/import_geo_data.py
pg_data_etl/database/actions/import_tabular_data.py
pg_data_etl/database/actions/load_from_dumpfile.py
pg_data_etl/database/actions/query/__init__.py
pg_data_etl/database/actions/query/data_nonspatial.py
pg_data_etl/database/actions/query/data_spatial.py
pg_data_etl/database/actions/query/execute.py
pg_data_etl/database/actions/query/lists.py
pg_data_etl/database/actions/query/simple.py
pg_data_etl/database/actions/query/update.py
pg_data_etl/database/actions/query/update_geo.py
pg_data_etl/database/actions/reports.py
pg_data_etl/helpers/__init__.py
pg_data_etl/helpers/commands.py
pg_data_etl/helpers/files.py
pg_data_etl/helpers/sql_tables.py
pg_data_etl/helpers/uri.py
pg_data_etl/settings/__init__.py
pg_data_etl/settings/make_config_file.py
pg_data_etl/settings/read_config_file.py
pg_data_etl-0.3.9.dist-info/entry_points.txt
pg_data_etl-0.3.9.dist-info/LICENSE
pg_data_etl-0.3.9.dist-info/WHEEL
pg_data_etl-0.3.9.dist-info/METADATA
pg_data_etl-0.3.9.dist-info/RECORD
