Metadata-Version: 2.1
Name: pg-data-etl
Version: 0.3.9
Summary: ETL tools for spatial data stored in postgres
Home-page: https://github.com/aaronfraint/pg-data-etl
License: GNU v3
Author: Aaron Fraint
Author-email: 38364429+aaronfraint@users.noreply.github.com
Requires-Python: >=3.8,<4.0
Classifier: License :: Other/Proprietary License
Classifier: Programming Language :: Python :: 3
Classifier: Programming Language :: Python :: 3.8
Classifier: Programming Language :: Python :: 3.9
Project-URL: Repository, https://github.com/aaronfraint/pg-data-etl
